LICENSE.txt
README.md
setup.cfg
setup.py
openhomedevice/__init__.py
openhomedevice/device.py
openhomedevice/didl_lite.py
openhomedevice.egg-info/PKG-INFO
openhomedevice.egg-info/SOURCES.txt
openhomedevice.egg-info/dependency_links.txt
openhomedevice.egg-info/requires.txt
openhomedevice.egg-info/top_level.txt