Metadata-Version: 2.1
Name: openhomedevice
Version: 2.2
Summary: Provides an API for requesting information from an Openhome device
Home-page: https://github.com/bazwilliams/openhomedevice
Author: Barry John Williams
Author-email: barry@bjw.me.uk
License: UNKNOWN
Download-URL: https://github.com/bazwilliams/openhomedevice/tarball/2.1
Keywords: upnp,dlna,openhome,linn,ds,music,render,async
Platform: UNKNOWN
Classifier: Programming Language :: Python :: 3
Classifier: License :: OSI Approved :: MIT License
Classifier: Operating System :: OS Independent
Requires-Python: >=3.6
License-File: LICENSE.txt
